byter/__init__.py
byter/constants.py
byter/reader.py
byter/utils.py
byter/writer.py
byter-0.0.2.dist-info/LICENSE
byter-0.0.2.dist-info/METADATA
byter-0.0.2.dist-info/WHEEL
byter-0.0.2.dist-info/top_level.txt
byter-0.0.2.dist-info/RECORD
