Metadata-Version: 2.1
Name: byter
Version: 0.0.2
Summary: Python binary object reader/writer
Home-page: https://github.com/sergeyshilin/byter
Author: Sergey Shilin
Author-email: shilinshtein@gmail.com
License: UNKNOWN
Platform: UNKNOWN
Classifier: Intended Audience :: Developers
Classifier: Natural Language :: English
Classifier: License :: OSI Approved :: Apache Software License
Classifier: Operating System :: OS Independent
Classifier: Programming Language :: Python :: 3
Requires-Python: >=3.6
